{
    "game": {
        "294910706250285056": {
            "level": 0,
            "xp": 20,
            "objects": {
                "diamonds": 0,
                "irons": 0,
                "golds": 0,
                "woods": 5
            },
            "bonus": {
                "xpBottle": 0,
                "ironPack": 0,
                "goldPack": 0,
                "woodPack": 0
            }
        },
        "392012706279981066": {
            "level": 0,
            "xp": 20,
            "objects": {
                "diamonds": 0,
                "irons": 0,
                "golds": 0,
                "woods": 5
            },
            "bonus": {
                "xpBottle": 0,
                "ironPack": 0,
                "goldPack": 0,
                "woodPack": 0
            }
        }
    }
}